odeSolver/__init__.py
odeSolver/odeSolver.py
svasir03_ode_module-0.0.3.dist-info/LICENSE
svasir03_ode_module-0.0.3.dist-info/METADATA
svasir03_ode_module-0.0.3.dist-info/WHEEL
svasir03_ode_module-0.0.3.dist-info/top_level.txt
svasir03_ode_module-0.0.3.dist-info/RECORD
