Metadata-Version: 2.1
Name: svasir03_ode_module
Version: 0.0.3
Summary: ODE solver
Author-email: Svante Sirviö <svante.sirvio03@gmail.com>
Classifier: Programming Language :: Python :: 3
Classifier: License :: OSI Approved :: MIT License
Classifier: Operating System :: OS Independent
Requires-Python: >=3.8
License-File: LICENSE
Requires-Dist: numpy >=1.26
